simulation_super_brownian_motions/__init__.py
simulation_super_brownian_motions/super_bm_simulation.py
simulation_super_brownian_motions-1.2.3.dist-info/LICENSE
simulation_super_brownian_motions-1.2.3.dist-info/METADATA
simulation_super_brownian_motions-1.2.3.dist-info/WHEEL
simulation_super_brownian_motions-1.2.3.dist-info/entry_points.txt
simulation_super_brownian_motions-1.2.3.dist-info/top_level.txt
simulation_super_brownian_motions-1.2.3.dist-info/RECORD
