Metadata-Version: 2.1
Name: simulation-super-brownian-motions
Version: 1.2.3
Summary: This is a package for simulating super Brownian motions.
Home-page: https://github.com/chenle02/Simulation_Super_Brownian_Motions
Author: Le Chen
Author-email: chenle02@gmail.com
Classifier: Programming Language :: Python :: 3
Classifier: License :: OSI Approved :: MIT License
Classifier: Operating System :: OS Independent
License-File: LICENSE
Requires-Dist: numpy
Requires-Dist: matplotlib
